Workbook

Sheet Overview
A1: Sum of Weights | B1: Maximum Possible Score | C1: Calculated Weighted Average Score | D1: Difference from Maximum Score
A2: =SUM(Scoring!E2:E140) -> 0 | B2: 10 | C2: =SUM(Scoring!H2:H140)/A2 -> 0 | D2: =B2-C2 -> 0
A4: Domain | B4: Action Count
A5: Manage the FinOps Practice | B5: 42 | U5: =SUMIF(Scoring!I2:I140,A5,Scoring!H2:H140)/SUMIF(Scoring!I2:I140,A5,Scoring!E2:E140) -> 0
A6: Optimize Usage & Cost | B6: 36 | U6: =SUMIF(Scoring!I2:I140,A6,Scoring!H2:H140)/SUMIF(Scoring!I2:I140,A6,Scoring!E2:E140) -> 0
A7: Quantify Business Value | B7: 31 | U7: =SUMIF(Scoring!I2:I140,A7,Scoring!H2:H140)/SUMIF(Scoring!I2:I140,A7,Scoring!E2:E140) -> 0
A8: Understand Usage & Cost | B8: 30 | U8: =SUMIF(Scoring!I2:I140,A8,Scoring!H2:H140)/SUMIF(Scoring!I2:I140,A8,Scoring!E2:E140) -> 0
B9: =SUM(Overview!$B$5:$B$8) -> 0
A11: Capability | B11: Action Count
A12: Allocation | B12: 7 | U12: =SUMIF(Scoring!J2:J140,A12,Scoring!H2:H140)/SUMIF(Scoring!J2:J140,A12,Scoring!E2:E140) -> 0
A13: Anomaly Management | B13: 7 | U13: =SUMIF(Scoring!J2:J140,A13,Scoring!H2:H140)/SUMIF(Scoring!J2:J140,A13,Scoring!E2:E140) -> 0
A14: Architecting & Workload Placement | B14: 12 | U14: =SUMIF(Scoring!J2:J140,A14,Scoring!H2:H140)/SUMIF(Scoring!J2:J140,A14,Scoring!E2:E140) -> 0
A15: Automation, Tools & Services | B15: 5 | U15: =SUMIF(Scoring!J2:J140,A15,Scoring!H2:H140)/SUMIF(Scoring!J2:J140,A15,Scoring!E2:E140) -> 0
A16: Budgeting | B16: 6 | U16: =SUMIF(Scoring!J2:J140,A16,Scoring!H2:H140)/SUMIF(Scoring!J2:J140,A16,Scoring!E2:E140) -> 0
A17: Data Ingestion | B17: 9 | U17: =SUMIF(Scoring!J2:J140,A17,Scoring!H2:H140)/SUMIF(Scoring!J2:J140,A17,Scoring!E2:E140) -> 0
A18: Executive Strategy Alignment | B18: 4 | U18: =SUMIF(Scoring!J2:J140,A18,Scoring!H2:H140)/SUMIF(Scoring!J2:J140,A18,Scoring!E2:E140) -> 0
A19: FinOps Assessment | B19: 5 | U19: =SUMIF(Scoring!J2:J140,A19,Scoring!H2:H140)/SUMIF(Scoring!J2:J140,A19,Scoring!E2:E140) -> 0
A20: FinOps Education & Enablement | B20: 5 | U20: =SUMIF(Scoring!J2:J140,A20,Scoring!H2:H140)/SUMIF(Scoring!J2:J140,A20,Scoring!E2:E140) -> 0
A21: FinOps Practice Operations | B21: 6 | U21: =SUMIF(Scoring!J2:J140,A21,Scoring!H2:H140)/SUMIF(Scoring!J2:J140,A21,Scoring!E2:E140) -> 0
A22: Forecasting | B22: 6 | U22: =SUMIF(Scoring!J2:J140,A22,Scoring!H2:H140)/SUMIF(Scoring!J2:J140,A22,Scoring!E2:E140) -> 0
A23: Governance, Policy & Risk | B23: 5 | U23: =SUMIF(Scoring!J2:J140,A23,Scoring!H2:H140)/SUMIF(Scoring!J2:J140,A23,Scoring!E2:E140) -> 0
A24: Intersecting Disciplines | B24: 6 | U24: =SUMIF(Scoring!J2:J140,A24,Scoring!H2:H140)/SUMIF(Scoring!J2:J140,A24,Scoring!E2:E140) -> 0
A25: Invoicing & Chargeback | B25: 6 | U25: =SUMIF(Scoring!J2:J140,A25,Scoring!H2:H140)/SUMIF(Scoring!J2:J140,A25,Scoring!E2:E140) -> 0
A26: KPIs & Benchmarking | B26: 6 | U26: =SUMIF(Scoring!J2:J140,A26,Scoring!H2:H140)/SUMIF(Scoring!J2:J140,A26,Scoring!E2:E140) -> 0
A27: Licensing & SaaS | B27: 6 | U27: =SUMIF(Scoring!J2:J140,A27,Scoring!H2:H140)/SUMIF(Scoring!J2:J140,A27,Scoring!E2:E140) -> 0
A28: Planning & Estimating | B28: 7 | U28: =SUMIF(Scoring!J2:J140,A28,Scoring!H2:H140)/SUMIF(Scoring!J2:J140,A28,Scoring!E2:E140) -> 0
A29: Rate Optimization | B29: 6 | U29: =SUMIF(Scoring!J2:J140,A29,Scoring!H2:H140)/SUMIF(Scoring!J2:J140,A29,Scoring!E2:E140) -> 0
A30: Reporting & Analytics | B30: 7 | U30: =SUMIF(Scoring!J2:J140,A30,Scoring!H2:H140)/SUMIF(Scoring!J2:J140,A30,Scoring!E2:E140) -> 0
A31: Sustainability | B31: 6 | U31: =SUMIF(Scoring!J2:J140,A31,Scoring!H2:H140)/SUMIF(Scoring!J2:J140,A31,Scoring!E2:E140) -> 0
A32: Unit Economics | B32: 6 | U32: =SUMIF(Scoring!J2:J140,A32,Scoring!H2:H140)/SUMIF(Scoring!J2:J140,A32,Scoring!E2:E140) -> 0
A33: Usage Optimization | B33: 6 | U33: =SUMIF(Scoring!J2:J140,A33,Scoring!H2:H140)/SUMIF(Scoring!J2:J140,A33,Scoring!E2:E140) -> 0
B34: =SUM(Overview!$B$12:$B$33) -> 0

Sheet Scoring
A1: domain | B1: capability | C1: action | D1: serial number | E1: weights | F1: formula | G1: scoring | H1: weighted score | I1: _domain | J1: _capability
A2: Understand Usage & Cost | B2: Data Ingestion | C2: Inventory All Data Sources | D2: 001 | E2: 0 | G2: 0: None | H2: =E2*VALUE(LEFT(G2, FIND(":", G2)-1)) -> 0 | I2: Understand Usage & Cost | J2: Data Ingestion
C3: Choose Data Landing Tooling | D3: 002 | E3: 0 | G3: 0: None | H3: =E3*VALUE(LEFT(G3, FIND(":", G3)-1)) -> 0 | I3: Understand Usage & Cost | J3: Data Ingestion
C4: Create Landing Zones & Controls | D4: 003 | E4: 0 | G4: 0: None | H4: =E4*VALUE(LEFT(G4, FIND(":", G4)-1)) -> 0 | I4: Understand Usage & Cost | J4: Data Ingestion
C5: Define Data Granularity & Frequency | D5: 004 | E5: 1 | G5: 0: Never | H5: =E5*VALUE(LEFT(G5, FIND(":", G5)-1)) -> 0 | I5: Understand Usage & Cost | J5: Data Ingestion
C6: Document Normalization Rules | D6: 005 | E6: 0 | G6: 0: None | H6: =E6*VALUE(LEFT(G6, FIND(":", G6)-1)) -> 0 | I6: Understand Usage & Cost | J6: Data Ingestion
C7: Implement Data Quality Checks | D7: 006 | E7: 1 | F7: * Define data quality (complete, valid, etc.) * Manual quality checks * Automated checks (null % on required fields/tags) * Response process and triage defined * SLAs defined and monitored * Integrate with communication and alerting tools * Integrate into CI/CD pipelines 10*Ceil(x/7) | G7: 0: No items completed | H7: =E7*VALUE(LEFT(G7, FIND(":", G7)-1)) -> 0 | I7: Understand Usage & Cost | J7: Data Ingestion
C8: Build Ingestion Anomaly Dashboards | D8: 007 | E8: 1 | F8: Not in order, gain points for each task * Manual or basic logs * Define key metrics (failures, latency, etc.) * Static Dashboard updated manually * Automated alerts for failures * Integrate with communication and alerting tools * Define Process & SLAs:RCAs completed for each * Tune out false positives 10*Ceil(x/7) | G8: 0: No items completed | H8: =E8*VALUE(LEFT(G8, FIND(":", G8)-1)) -> 0 | I8: Understand Usage & Cost | J8: Data Ingestion
C9: Optimize Pipelines for Timeliness | D9: 008 | E9: 0 | G9: 0: None | H9: =E9*VALUE(LEFT(G9, FIND(":", G9)-1)) -> 0 | I9: Understand Usage & Cost | J9: Data Ingestion
C10: Define ingestion frequency; include mandatory metadata. | D10: 135 | E10: 1 | G10: 0: Never | H10: =E10*VALUE(LEFT(G10, FIND(":", G10)-1)) -> 0 | I10: Understand Usage & Cost | J10: Data Ingestion
B11: Allocation | C11: Define Metadata & Hierarchy Strategy | D11: 009 | E11: 1 | F11: Increasing Granularity and Visibility * Define metadata to track (org, dept, cost center, team, app, etc.) * Create the hierarchy for each category of metadata (ex teams per dept, cost centers in an org) 10*Ceil(x/2) | G11: 0: No items completed | H11: =E11*VALUE(LEFT(G11, FIND(":", G11)-1)) -> 0 | I11: Understand Usage & Cost | J11: Allocation
C12: Identify Shared Costs & Rules | D12: 010 | E12: 1 | F12: Unallocated Shared CSP Effective Cloud Cost/ Total CSP Effective Cloud Cost | G12: 0: 0% | H12: =E12*VALUE(LEFT(G12, FIND(":", G12)-1)) -> 0 | I12: Understand Usage & Cost | J12: Allocation
C13: Publish Allocation Taxonomy | D13: 011 | E13: 1 | F13: Increasing Granularity and Visibility * Document as part of tagging strategy and enforcement * Teams have visibility into where their resources fit into the hierarchy 10*Ceil(x/2) | G13: 0: No items completed | H13: =E13*VALUE(LEFT(G13, FIND(":", G13)-1)) -> 0 | I13: Understand Usage & Cost | J13: Allocation
C14: Implement Tagging Standards | D14: 012 | E14: 1 | F14: Percentage of total costs that are tagged for Each Required Tag | G14: 0: 0% | H14: =E14*VALUE(LEFT(G14, FIND(":", G14)-1)) -> 0 | I14: Understand Usage & Cost | J14: Allocation
C15: Validate Compliance & Report Gaps | D15: 013 | E15: 1 | F15: x = Total Effective Costs Associated with Unallocated CSP Cloud Resources During y = Total CSP Cloud Costs During a Period of Time x / y | G15: 0: 0% | H15: =E15*VALUE(LEFT(G15, FIND(":", G15)-1)) -> 0 | I15: Understand Usage & Cost | J15: Allocation
C16: Automate Tagging & Enforcement | D16: 014 | E16: 1 | F16: Effectiveness/Effort by strategy * Manually asking teams to tag resources * Remove untagged resources after time threshold * Block deployments without proper tags * Automatically tag based on CI/CD creator and team 10*Ceil(x/4) | G16: 0: No items completed | H16: =E16*VALUE(LEFT(G16, FIND(":", G16)-1)) -> 0 | I16: Understand Usage & Cost | J16: Allocation
C17: Iterate Strategies & Communicate | D17: 015 | E17: 0 | G17: 0: None | H17: =E17*VALUE(LEFT(G17, FIND(":", G17)-1)) -> 0 | I17: Understand Usage & Cost | J17: Allocation
B18: Reporting & Analytics | C18: Gather Requirements & Define KPIs | D18: 016 | E18: 0 | G18: 0: None | H18: =E18*VALUE(LEFT(G18, FIND(":", G18)-1)) -> 0 | I18: Understand Usage & Cost | J18: Reporting & Analytics
C19: Enrich Billing with Business Logic | D19: 017 | E19: 1 | F19: * Manual adjustments to invoices and teams * Define Business Rules for sharing discounts, RI/SP, etc. * Automate adjustment calculations monthly in arrears * Automate mappings into reporting platform for realtime adjustments 10*Ceil(x/4) | G19: 0: No items completed | H19: =E19*VALUE(LEFT(G19, FIND(":", G19)-1)) -> 0 | I19: Understand Usage & Cost | J19: Reporting & Analytics
C20: Build Dashboards for All Views | D20: 018 | E20: 1 | F20: * Dashboard for showback * Dashboard where teams can dive in to investigate costs * Ad-hoc dashboards available to teams * Dashboards for key metrics tracking (tagging, waste, etc.) 10*Ceil(x/4) | G20: 0: No items completed | H20: =E20*VALUE(LEFT(G20, FIND(":", G20)-1)) -> 0 | I20: Understand Usage & Cost | J20: Reporting & Analytics
C21: Publish Documentation & Support | D21: 019 | E21: 0 | G21: 0: None | H21: =E21*VALUE(LEFT(G21, FIND(":", G21)-1)) -> 0 | I21: Understand Usage & Cost | J21: Reporting & Analytics
C22: Embed Reports in Workflows | D22: 020 | E22: 1 | G22: 0: No alerting in workflow tools | H22: =E22*VALUE(LEFT(G22, FIND(":", G22)-1)) -> 0 | I22: Understand Usage & Cost | J22: Reporting & Analytics
C23: Track Adoption & Manage Changes | D23: 021 | E23: 0 | G23: 0: None | H23: =E23*VALUE(LEFT(G23, FIND(":", G23)-1)) -> 0 | I23: Understand Usage & Cost | J23: Reporting & Analytics
C24: Iterate Based on Feedback | D24: 022 | E24: 0 | G24: 0: None | H24: =E24*VALUE(LEFT(G24, FIND(":", G24)-1)) -> 0 | I24: Understand Usage & Cost | J24: Reporting & Analytics
B25: Anomaly Management | C25: Configure Cost Spike Detection | D25: 023 | E25: 1 | F25: * Manual inspection of spikes * Out-of-the-box tool based anomaly alerts * Custom simple increase alert calculations * Custom alerts per business unit, team, etc. * Alerts per unit costs above thresholds 10*Ceil(x/5) | G25: 0: No items completed | H25: =E25*VALUE(LEFT(G25, FIND(":", G25)-1)) -> 0 | I25: Understand Usage & Cost | J25: Anomaly Management
C26: Define Severity & Response SLAs | D26: 024 | E26: 1 | F26: * Defined severity tiers * Thresholds associated with severity tiers are defined * Defined and adhered to response SLAs * Published response runbooks * Runbook percent successful or completed * RCA completed after alerts 10*Ceil(x/6) | G26: 0: No items completed | H26: =E26*VALUE(LEFT(G26, FIND(":", G26)-1)) -> 0 | I26: Understand Usage & Cost | J26: Anomaly Management
C27: Automate Alert Routing | D27: 025 | E27: 1 | G27: 0: No alerting to any owners | H27: =E27*VALUE(LEFT(G27, FIND(":", G27)-1)) -> 0 | I27: Understand Usage & Cost | J27: Anomaly Management
C28: Record Anomaly Context & Timeline | D28: 026 | E28: 0 | G28: 0: None | H28: =E28*VALUE(LEFT(G28, FIND(":", G28)-1)) -> 0 | I28: Understand Usage & Cost | J28: Anomaly Management
C29: Analyze Root Causes & Fix Issues | D29: 027 | E29: 0 | G29: 0: None | H29: =E29*VALUE(LEFT(G29, FIND(":", G29)-1)) -> 0 | I29: Understand Usage & Cost | J29: Anomaly Management
C30: Track Metrics & Avoidance Rates | D30: 028 | E30: 1 | F30: * Number of detections per time period * Number of detections over threshold * Time to send notifications to stakeholders * Time to validate anomaly * Resolution Time/SLA adherence * False positive rate * Cost Avoidance due to detection * Percent anomalies addressed 10*Ceil(x/8) | G30: 0: No items completed | H30: =E30*VALUE(LEFT(G30, FIND(":", G30)-1)) -> 0 | I30: Understand Usage & Cost | J30: Anomaly Management
C31: Tune Thresholds to Reduce Noise | D31: 029 | E31: 0 | G31: 0: None | H31: =E31*VALUE(LEFT(G31, FIND(":", G31)-1)) -> 0 | I31: Understand Usage & Cost | J31: Anomaly Management
A32: Quantify Business Value | B32: Planning & Estimating | C32: Define Estimating Scope & Policy | D32: 030 | E32: 1 | F32: * Defined scope of each project to be estimated * Developed list of known inputs to the project * Have a process to determine what may be missing from the inputs or scope * Have a policy review to determine additional needs for inputs or scope * For each component of the estimate, list all assumptions 10*Ceil(x/5) | G32: 0: No items completed | H32: =E32*VALUE(LEFT(G32, FIND(":", G32)-1)) -> 0 | I32: Quantify Business Value | J32: Planning & Estimating
C33: Agree on Pricing Assumptions | D33: 031 | E33: 1 | F33: * Inventory possible commitment based discounts (RIs, Savings Plans, CUDs, etc.) available for deployed resources * Consider any private negotiated line item discounts vs public RI/CUD discounts * Set resource type standards to make use of spend commitments while maintaining needs of the business * Scenario plan commitment options versus potential changes in resources * Reference commit allocation strategy to calculate cost impact of shared scope vs private account commitments 10*Ceil(x/5) | G33: 0: No items completed | H33: =E33*VALUE(LEFT(G33, FIND(":", G33)-1)) -> 0 | I33: Quantify Business Value | J33: Planning & Estimating
C34: Select Estimation Methods | D34: 032 | E34: 1 | F34: * Use pricing lists or pricing calculators to estimate workload spend * Run workloads as trial experiments to get baseline spend * Estimate workload costs based on similar applications already deployed in your environment * Determine fixed costs vs formulas for variable costs due to growth of workloads * Factor in discounts and uptime metrics to determine accurate spend vs list 10*Ceil(x/5) | G34: 0: No items completed | H34: =E34*VALUE(LEFT(G34, FIND(":", G34)-1)) -> 0 | I34: Quantify Business Value | J34: Planning & Estimating
C35: Include Sustainability Impacts | D35: 033 | E35: 1 | F35: 1. Calculate kg of carbon dioxide equivalents (kgCO2e), or similar, for new and ongoing workloads 2. Compare carbon calculations with targets for new projects and overall consumption | G35: 0: No items completed | H35: =E35*VALUE(LEFT(G35, FIND(":", G35)-1)) -> 0 | I35: Quantify Business Value | J35: Planning & Estimating
C36: Establish Scenario Decision Process | D36: 034 | E36: 1 | F36: * Define and follow process for gathering deployment plans from teams * Determine timeline for each new project to adjust the forecast during that time * Determine how optimizations and lower run rate will impact the forecast on a rolling basis 10*Ceil(x/3) | G36: 0: No items completed | H36: =E36*VALUE(LEFT(G36, FIND(":", G36)-1)) -> 0 | I36: Quantify Business Value | J36: Planning & Estimating
C37: Report Estimate Accuracy | D37: 035 | E37: 1 | G37: 0: 0% | H37: =E37*VALUE(LEFT(G37, FIND(":", G37)-1)) -> 0 | I37: Quantify Business Value | J37: Planning & Estimating
C38: Coach Engineering on Estimates | D38: 036 | E38: 1 | F38: * Refer teams to Documented Estimating Scope & Policy and include these methods in trainings * Teams track baseline spend for resources they own, and share changes to baseline with leadership * Teams will share updates about their change in usage of shared resources and dependencies * Track team adoption of better estimates via KPIs around baseline or plan vs actuals 10*Ceil(x/4) | G38: 0: No items completed | H38: =E38*VALUE(LEFT(G38, FIND(":", G38)-1)) -> 0 | I38: Quantify Business Value | J38: Planning & Estimating
B39: Forecasting | C39: Establish Forecasting Approach | D39: 037 | E39: 0 | G39: 0: None | H39: =E39*VALUE(LEFT(G39, FIND(":", G39)-1)) -> 0 | I39: Quantify Business Value | J39: Forecasting
C40: Collect Business Drivers Regularly | D40: 038 | E40: 1 | F40: * Data based on existing patterns * Proactive investigations and interviews with teams * Proactive self reporting by the business and/or teams * 100% catch rate of spikes before they happen 10*Ceil(x/4) | G40: 0: No items completed | H40: =E40*VALUE(LEFT(G40, FIND(":", G40)-1)) -> 0 | I40: Quantify Business Value | J40: Forecasting
C41: Run & Refresh Rolling Forecasts | D41: 039 | E41: 1 | G41: 0: None | H41: =E41*VALUE(LEFT(G41, FIND(":", G41)-1)) -> 0 | I41: Quantify Business Value | J41: Forecasting
C42: Compare Forecast to Actual | D42: 040 | E42: 1 | F42: ((Forecasted Public Cloud Spend – Actual Public Cloud Spend) / Forecasted Public Cloud Spend) | G42: 0: 0% | H42: =E42*VALUE(LEFT(G42, FIND(":", G42)-1)) -> 0 | I42: Quantify Business Value | J42: Forecasting
C43: Automate Variance Alerts | D43: 041 | E43: 1 | G43: 0: No alerting | H43: =E43*VALUE(LEFT(G43, FIND(":", G43)-1)) -> 0 | I43: Quantify Business Value | J43: Forecasting
C44: Feed Learnings into Budgeting & Commitments | D44: 042 | E44: 1 | F44: * Periodic review of budget vs forecast * Track when projects are forecasted to go over budget * Process to request more budget for projects going over * RCA to determine cause of budget over run 10*Ceil(x/4) | G44: 0: No items completed | H44: =E44*VALUE(LEFT(G44, FIND(":", G44)-1)) -> 0 | I44: Quantify Business Value | J44: Forecasting
B45: Budgeting | C45: Define Budgeting Strategy | D45: 043 | E45: 1 | G45: 0: Does not exist | H45: =E45*VALUE(LEFT(G45, FIND(":", G45)-1)) -> 0 | I45: Quantify Business Value | J45: Budgeting
C46: Integrate Rolling Forecasts | D46: 044 | E46: 1 | G46: 0: Does not exist | H46: =E46*VALUE(LEFT(G46, FIND(":", G46)-1)) -> 0 | I46: Quantify Business Value | J46: Budgeting
C47: Increase Shared Cost Coverage | D47: 045 | E47: 0 | G47: 0: None | H47: =E47*VALUE(LEFT(G47, FIND(":", G47)-1)) -> 0 | I47: Quantify Business Value | J47: Budgeting
C48: Publish Budget vs Actual Reports | D48: 046 | E48: 0 | G48: 0: None | H48: =E48*VALUE(LEFT(G48, FIND(":", G48)-1)) -> 0 | I48: Quantify Business Value | J48: Budgeting
C49: Automate Budget Threshold Alerts | D49: 047 | E49: 0 | G49: 0: None | H49: =E49*VALUE(LEFT(G49, FIND(":", G49)-1)) -> 0 | I49: Quantify Business Value | J49: Budgeting
C50: Review & Adapt Budget Strategy | D50: 048 | E50: 0 | G50: 0: None | H50: =E50*VALUE(LEFT(G50, FIND(":", G50)-1)) -> 0 | I50: Quantify Business Value | J50: Budgeting
B51: KPIs & Benchmarking | C51: Select KPIs & Measurement Scope | D51: 049 | E51: 0 | G51: 0: None | H51: =E51*VALUE(LEFT(G51, FIND(":", G51)-1)) -> 0 | I51: Quantify Business Value | J51: KPIs & Benchmarking
C52: Validate Tagging for Comparability | D52: 050 | E52: 0 | G52: 0: None | H52: =E52*VALUE(LEFT(G52, FIND(":", G52)-1)) -> 0 | I52: Quantify Business Value | J52: KPIs & Benchmarking
C53: Choose Internal vs External Benchmarks | D53: 051 | E53: 0 | G53: 0: None | H53: =E53*VALUE(LEFT(G53, FIND(":", G53)-1)) -> 0 | I53: Quantify Business Value | J53: KPIs & Benchmarking
C54: Stand Up Internal Benchmarking | D54: 052 | E54: 0 | G54: 0: None | H54: =E54*VALUE(LEFT(G54, FIND(":", G54)-1)) -> 0 | I54: Quantify Business Value | J54: KPIs & Benchmarking
C55: Track Trends & Compare Over Time | D55: 053 | E55: 1 | G55: 0: No review of trends | H55: =E55*VALUE(LEFT(G55, FIND(":", G55)-1)) -> 0 | I55: Quantify Business Value | J55: KPIs & Benchmarking
C56: Translate Gaps to Initiatives | D56: 054 | E56: 0 | G56: 0: None | H56: =E56*VALUE(LEFT(G56, FIND(":", G56)-1)) -> 0 | I56: Quantify Business Value | J56: KPIs & Benchmarking
B57: Unit Economics | C57: Define Business-Relevant Units | D57: 055 | E57: 1 | F57: * Define cost drivers from finance/business * Gather metrics on a cadence * Set goals/targets * Set up forecasting and anomaly detection on units 10*Ceil(x/4) | G57: 0: No items completed | H57: =E57*VALUE(LEFT(G57, FIND(":", G57)-1)) -> 0 | I57: Quantify Business Value | J57: Unit Economics
C58: Document Inputs & Formulas | D58: 056 | E58: 0 | G58: 0: None | H58: =E58*VALUE(LEFT(G58, FIND(":", G58)-1)) -> 0 | I58: Quantify Business Value | J58: Unit Economics
C59: Build Unit Cost Dashboards | D59: 057 | E59: 0 | G59: 0: None | H59: =E59*VALUE(LEFT(G59, FIND(":", G59)-1)) -> 0 | I59: Quantify Business Value | J59: Unit Economics
C60: Set Review Cadence & Targets | D60: 058 | E60: 0 | G60: 0: None | H60: =E60*VALUE(LEFT(G60, FIND(":", G60)-1)) -> 0 | I60: Quantify Business Value | J60: Unit Economics
C61: Use Metrics to Prioritize Investments | D61: 059 | E61: 0 | G61: 0: None | H61: =E61*VALUE(LEFT(G61, FIND(":", G61)-1)) -> 0 | I61: Quantify Business Value | J61: Unit Economics
C62: Communicate Unit Cost Wins | D62: 060 | E62: 1 | G62: 0: None | H62: =E62*VALUE(LEFT(G62, FIND(":", G62)-1)) -> 0 | I62: Quantify Business Value | J62: Unit Economics
A63: Optimize Usage & Cost | B63: Architecting & Workload Placement | C63: Establish Architecture Review Process | D63: 061 | E63: 1 | G63: 0: Does not exist | H63: =E63*VALUE(LEFT(G63, FIND(":", G63)-1)) -> 0 | I63: Optimize Usage & Cost | J63: Architecting & Workload Placement
C64: Assess Workloads for Modernization | D64: 062 | E64: 1 | F64: * Define process to address notifications from CSPs * Define cadence for review * Define exception criteria * Define thresholds to change * Combine with architecture analysis for SP & RIs 10*Ceil(x/5) | G64: 0: No items completed | H64: =E64*VALUE(LEFT(G64, FIND(":", G64)-1)) -> 0 | I64: Optimize Usage & Cost | J64: Architecting & Workload Placement
C65: Estimate Trade-Offs & Document Cases | D65: 063 | E65: 1 | G65: 0: No documented method | H65: =E65*VALUE(LEFT(G65, FIND(":", G65)-1)) -> 0 | I65: Optimize Usage & Cost | J65: Architecting & Workload Placement
C66: Implement Iteratively & Measure Results | D66: 064 | E66: 0 | G66: 0: None | H66: =E66*VALUE(LEFT(G66, FIND(":", G66)-1)) -> 0 | I66: Optimize Usage & Cost | J66: Architecting & Workload Placement
C67: Publish Benefits & Update References | D67: 065 | E67: 0 | G67: 0: None | H67: =E67*VALUE(LEFT(G67, FIND(":", G67)-1)) -> 0 | I67: Optimize Usage & Cost | J67: Architecting & Workload Placement
C68: Strengthen Architecture Collaboration | D68: 066 | E68: 0 | G68: 0: None | H68: =E68*VALUE(LEFT(G68, FIND(":", G68)-1)) -> 0 | I68: Optimize Usage & Cost | J68: Architecting & Workload Placement
C69: Create Workload Selection Criteria | D69: 118 | E69: 0 | G69: 0: None | H69: =E69*VALUE(LEFT(G69, FIND(":", G69)-1)) -> 0 | I69: Optimize Usage & Cost | J69: Architecting & Workload Placement
C70: Define Success Criteria & Scope | D70: 119 | E70: 0 | G70: 0: None | H70: =E70*VALUE(LEFT(G70, FIND(":", G70)-1)) -> 0 | I70: Optimize Usage & Cost | J70: Architecting & Workload Placement
C71: Enforce Tagging at Onboarding | D71: 120 | E71: 1 | F71: * Process defined for new accounts and resources deployed * Train teams on process * Automate process 10*Ceil(x/3) | G71: 0: No items completed | H71: =E71*VALUE(LEFT(G71, FIND(":", G71)-1)) -> 0 | I71: Optimize Usage & Cost | J71: Architecting & Workload Placement
C72: Align Timelines with Budgets | D72: 121 | E72: 0 | G72: 0: None | H72: =E72*VALUE(LEFT(G72, FIND(":", G72)-1)) -> 0 | I72: Optimize Usage & Cost | J72: Architecting & Workload Placement
C73: Start with Lower Environments | D73: 122 | E73: 0 | G73: 0: None | H73: =E73*VALUE(LEFT(G73, FIND(":", G73)-1)) -> 0 | I73: Optimize Usage & Cost | J73: Architecting & Workload Placement
C74: Review Outcomes & Adjust Patterns | D74: 123 | E74: 0 | G74: 0: None | H74: =E74*VALUE(LEFT(G74, FIND(":", G74)-1)) -> 0 | I74: Optimize Usage & Cost | J74: Architecting & Workload Placement
B75: Usage Optimization | C75: Define Optimization Strategy | D75: 067 | E75: 0 | G75: 0: None | H75: =E75*VALUE(LEFT(G75, FIND(":", G75)-1)) -> 0 | I75: Optimize Usage & Cost | J75: Usage Optimization
C76: Inventory & Classify Workloads | D76: 068 | E76: 1 | G76: 0: No teardown/shutdown policy | H76: =E76*VALUE(LEFT(G76, FIND(":", G76)-1)) -> 0 | I76: Optimize Usage & Cost | J76: Usage Optimization
C77: Collect Metrics & Identify Candidates | D77: 069 | E77: 1 | G77: 0: 0% | H77: =E77*VALUE(LEFT(G77, FIND(":", G77)-1)) -> 0 | I77: Optimize Usage & Cost | J77: Usage Optimization
C78: Partner on Scheduling Actions | D78: 070 | E78: 0 | G78: 0: None | H78: =E78*VALUE(LEFT(G78, FIND(":", G78)-1)) -> 0 | I78: Optimize Usage & Cost | J78: Usage Optimization
C79: Gamify Adoption & Celebrate Wins | D79: 071 | E79: 0 | G79: 0: None | H79: =E79*VALUE(LEFT(G79, FIND(":", G79)-1)) -> 0 | I79: Optimize Usage & Cost | J79: Usage Optimization
C80: Track KPIs & Document Playbooks | D80: 072 | E80: 0 | G80: 0: None | H80: =E80*VALUE(LEFT(G80, FIND(":", G80)-1)) -> 0 | I80: Optimize Usage & Cost | J80: Usage Optimization
B81: Rate Optimization | C81: Document Commitment Strategy | D81: 079 | E81: 1 | G81: 0: Not done | H81: =E81*VALUE(LEFT(G81, FIND(":", G81)-1)) -> 0 | I81: Optimize Usage & Cost | J81: Rate Optimization
C82: Build Commitment Analysis Process | D82: 080 | E82: 1 | G82: 0: Not done | H82: =E82*VALUE(LEFT(G82, FIND(":", G82)-1)) -> 0 | I82: Optimize Usage & Cost | J82: Rate Optimization
C83: Purchase Commitments Regularly | D83: 081 | E83: 0 | G83: 0: None | H83: =E83*VALUE(LEFT(G83, FIND(":", G83)-1)) -> 0 | I83: Optimize Usage & Cost | J83: Rate Optimization
C84: Track ROI & Notify Owners | D84: 082 | E84: 0 | G84: 0: None | H84: =E84*VALUE(LEFT(G84, FIND(":", G84)-1)) -> 0 | I84: Optimize Usage & Cost | J84: Rate Optimization
C85: Allocate Upfront Costs Transparently | D85: 083 | E85: 0 | G85: 0: None | H85: =E85*VALUE(LEFT(G85, FIND(":", G85)-1)) -> 0 | I85: Optimize Usage & Cost | J85: Rate Optimization
C86: Leverage Spot & Negotiated Discounts | D86: 084 | E86: 1 | F86: * Process for evaluating spot periodically * Tag for date last reviewed * New deployments get reviewed beforehand * Define requirements for spot * Have exception process and expiration date 10*Ceil(x/5) | G86: 0: No items completed | H86: =E86*VALUE(LEFT(G86, FIND(":", G86)-1)) -> 0 | I86: Optimize Usage & Cost | J86: Rate Optimization
B87: Licensing & SaaS | C87: Inventory Licenses & Map Resources | D87: 073 | E87: 1 | G87: 0: 0% | H87: =E87*VALUE(LEFT(G87, FIND(":", G87)-1)) -> 0 | I87: Optimize Usage & Cost | J87: Licensing & SaaS
C88: Document Licensing Models | D88: 074 | E88: 0 | G88: 0: None | H88: =E88*VALUE(LEFT(G88, FIND(":", G88)-1)) -> 0 | I88: Optimize Usage & Cost | J88: Licensing & SaaS
C89: Integrate Billing with Procurement | D89: 075 | E89: 0 | G89: 0: None | H89: =E89*VALUE(LEFT(G89, FIND(":", G89)-1)) -> 0 | I89: Optimize Usage & Cost | J89: Licensing & SaaS
C90: Validate Utilization & Remediate | D90: 076 | E90: 1 | G90: 0: Not done | H90: =E90*VALUE(LEFT(G90, FIND(":", G90)-1)) -> 0 | I90: Optimize Usage & Cost | J90: Licensing & SaaS
C91: Influence Workload Design Choices | D91: 077 | E91: 0 | G91: 0: None | H91: =E91*VALUE(LEFT(G91, FIND(":", G91)-1)) -> 0 | I91: Optimize Usage & Cost | J91: Licensing & SaaS
C92: Publish License Spend & Utilization | D92: 078 | E92: 0 | G92: 0: None | H92: =E92*VALUE(LEFT(G92, FIND(":", G92)-1)) -> 0 | I92: Optimize Usage & Cost | J92: Licensing & SaaS
B93: Sustainability | C93: Aggregate emissions data by region/service/account with lineage. | D93: 085 | E93: 0 | G93: 0: None | H93: =E93*VALUE(LEFT(G93, FIND(":", G93)-1)) -> 0 | I93: Optimize Usage & Cost | J93: Sustainability
C94: Define sustainability metrics/targets. | D94: 086 | E94: 0 | G94: 0: None | H94: =E94*VALUE(LEFT(G94, FIND(":", G94)-1)) -> 0 | I94: Optimize Usage & Cost | J94: Sustainability
C95: Include carbon impact in migration/optimization decisions and PRDs. | D95: 087 | E95: 0 | G95: 0: None | H95: =E95*VALUE(LEFT(G95, FIND(":", G95)-1)) -> 0 | I95: Optimize Usage & Cost | J95: Sustainability
C96: Enable engineering with carbon-aware data and scheduling guidance. | D96: 088 | E96: 0 | G96: 0: None | H96: =E96*VALUE(LEFT(G96, FIND(":", G96)-1)) -> 0 | I96: Optimize Usage & Cost | J96: Sustainability
C97: Continuously improve data quality and report progress on dashboards. | D97: 089 | E97: 0 | G97: 0: None | H97: =E97*VALUE(LEFT(G97, FIND(":", G97)-1)) -> 0 | I97: Optimize Usage & Cost | J97: Sustainability
C98: Tie sustainability wins to cost efficiency where possible. | D98: 090 | E98: 0 | G98: 0: None | H98: =E98*VALUE(LEFT(G98, FIND(":", G98)-1)) -> 0 | I98: Optimize Usage & Cost | J98: Sustainability
A99: Manage the FinOps Practice | B99: Executive Strategy Alignment | C99: Establish Executive Sponsorship | D99: 136 | E99: 1 | G99: 0: No executive sponsor identified | H99: =E99*VALUE(LEFT(G99, FIND(":", G99)-1)) -> 0 | I99: Manage the FinOps Practice | J99: Executive Strategy Alignment
C100: Define Decision Rights & Guardrails | D100: 137 | E100: 1 | F100: * Document decision rights and approval authority for technology spend * Define and publish spend guardrails with named owners * Establish escalation path for spend exceptions 10*Ceil(x/3) | G100: 0: No items completed | H100: =E100*VALUE(LEFT(G100, FIND(":", G100)-1)) -> 0 | I100: Manage the FinOps Practice | J100: Executive Strategy Alignment
...
