Workbook

Sheet Overview
A1: Sum of Weights | B1: Maximum Possible Score | C1: Calculated Weighted Average Score | D1: Difference from Maximum Score
A2: =SUM(Scoring!F2:F134) -> 0 | B2: 10 | C2: =SUM(Scoring!I2:I134)/A2 -> 0 | D2: =B2-C2 -> 0
A4: Domain | B4: Action Count
A5: Governance | B5: 5 | U5: =SUMIF(Scoring!J2:J134,A5,Scoring!I2:I134)/SUMIF(Scoring!J2:J134,A5,Scoring!F2:F134) -> 0
A6: Manage the FinOps Practice | B6: 37 | U6: =SUMIF(Scoring!J2:J134,A6,Scoring!I2:I134)/SUMIF(Scoring!J2:J134,A6,Scoring!F2:F134) -> 0
A7: Quantify Business Value | B7: 31 | U7: =SUMIF(Scoring!J2:J134,A7,Scoring!I2:I134)/SUMIF(Scoring!J2:J134,A7,Scoring!F2:F134) -> 0
A8: Usage & Cost | B8: 60 | U8: =SUMIF(Scoring!J2:J134,A8,Scoring!I2:I134)/SUMIF(Scoring!J2:J134,A8,Scoring!F2:F134) -> 0
B9: =SUM(Overview!$B$5:$B$8) -> 0
A11: Capability | B11: Action Count
A12: Allocation | B12: 7 | U12: =SUMIF(Scoring!K2:K134,A12,Scoring!I2:I134)/SUMIF(Scoring!K2:K134,A12,Scoring!F2:F134) -> 0
A13: Anomaly Management | B13: 7 | U13: =SUMIF(Scoring!K2:K134,A13,Scoring!I2:I134)/SUMIF(Scoring!K2:K134,A13,Scoring!F2:F134) -> 0
A14: Architecting & Workload Placement | B14: 12 | U14: =SUMIF(Scoring!K2:K134,A14,Scoring!I2:I134)/SUMIF(Scoring!K2:K134,A14,Scoring!F2:F134) -> 0
A15: Automation, Tools & Services | B15: 5 | U15: =SUMIF(Scoring!K2:K134,A15,Scoring!I2:I134)/SUMIF(Scoring!K2:K134,A15,Scoring!F2:F134) -> 0
A16: Budgeting | B16: 6 | U16: =SUMIF(Scoring!K2:K134,A16,Scoring!I2:I134)/SUMIF(Scoring!K2:K134,A16,Scoring!F2:F134) -> 0
A17: Data Ingestion | B17: 9 | U17: =SUMIF(Scoring!K2:K134,A17,Scoring!I2:I134)/SUMIF(Scoring!K2:K134,A17,Scoring!F2:F134) -> 0
A18: Executive Strategy Alignment | B18: 4 | U18: =SUMIF(Scoring!K2:K134,A18,Scoring!I2:I134)/SUMIF(Scoring!K2:K134,A18,Scoring!F2:F134) -> 0
A19: FinOps Assessment | B19: 5 | U19: =SUMIF(Scoring!K2:K134,A19,Scoring!I2:I134)/SUMIF(Scoring!K2:K134,A19,Scoring!F2:F134) -> 0
A20: FinOps Education & Enablement | B20: 5 | U20: =SUMIF(Scoring!K2:K134,A20,Scoring!I2:I134)/SUMIF(Scoring!K2:K134,A20,Scoring!F2:F134) -> 0
A21: FinOps Practice Operations | B21: 6 | U21: =SUMIF(Scoring!K2:K134,A21,Scoring!I2:I134)/SUMIF(Scoring!K2:K134,A21,Scoring!F2:F134) -> 0
A22: Forecasting | B22: 6 | U22: =SUMIF(Scoring!K2:K134,A22,Scoring!I2:I134)/SUMIF(Scoring!K2:K134,A22,Scoring!F2:F134) -> 0
A23: Intersecting Disciplines | B23: 6 | U23: =SUMIF(Scoring!K2:K134,A23,Scoring!I2:I134)/SUMIF(Scoring!K2:K134,A23,Scoring!F2:F134) -> 0
A24: Invoicing & Chargeback | B24: 6 | U24: =SUMIF(Scoring!K2:K134,A24,Scoring!I2:I134)/SUMIF(Scoring!K2:K134,A24,Scoring!F2:F134) -> 0
A25: KPIs & Benchmarking | B25: 6 | U25: =SUMIF(Scoring!K2:K134,A25,Scoring!I2:I134)/SUMIF(Scoring!K2:K134,A25,Scoring!F2:F134) -> 0
A26: Licensing & SaaS | B26: 6 | U26: =SUMIF(Scoring!K2:K134,A26,Scoring!I2:I134)/SUMIF(Scoring!K2:K134,A26,Scoring!F2:F134) -> 0
A27: Planning & Estimating | B27: 7 | U27: =SUMIF(Scoring!K2:K134,A27,Scoring!I2:I134)/SUMIF(Scoring!K2:K134,A27,Scoring!F2:F134) -> 0
A28: Policy | B28: 5 | U28: =SUMIF(Scoring!K2:K134,A28,Scoring!I2:I134)/SUMIF(Scoring!K2:K134,A28,Scoring!F2:F134) -> 0
A29: Rate Optimization | B29: 6 | U29: =SUMIF(Scoring!K2:K134,A29,Scoring!I2:I134)/SUMIF(Scoring!K2:K134,A29,Scoring!F2:F134) -> 0
A30: Reporting & Analytics | B30: 7 | U30: =SUMIF(Scoring!K2:K134,A30,Scoring!I2:I134)/SUMIF(Scoring!K2:K134,A30,Scoring!F2:F134) -> 0
A31: Unit Economics | B31: 6 | U31: =SUMIF(Scoring!K2:K134,A31,Scoring!I2:I134)/SUMIF(Scoring!K2:K134,A31,Scoring!F2:F134) -> 0
A32: Usage Optimization | B32: 6 | U32: =SUMIF(Scoring!K2:K134,A32,Scoring!I2:I134)/SUMIF(Scoring!K2:K134,A32,Scoring!F2:F134) -> 0
B33: =SUM(Overview!$B$12:$B$32) -> 0

Sheet Scoring
A1: domain | B1: capability | C1: action | D1: serial number | E1: version | F1: weights | G1: formula | H1: scoring | I1: weighted score | J1: _domain | K1: _capability
A2: Manage the FinOps Practice | B2: FinOps Assessment | C2: Define Assessment Scope & Goals | D2: 113 | E2: 1.1.0 | F2: 1 | G2: * Select which teams or groups are in scope for the planned assessments * Select which capabilities/actions are in scope for each group's assessment * Select weights for each included action based on goals of the assessment and importance to the business * Set a preliminary target score for each included action to use for comparison 10*Ceil(x/4) | H2: 0: 0 items completed | I2: =F2*VALUE(LEFT(H2, FIND(":", H2)-1)) -> 0 | J2: Manage the FinOps Practice | K2: FinOps Assessment
C3: Collect Standardized Assessment Inputs | D3: 114 | E3: 1.1.0 | F3: 1 | G3: * Use objective (not subjective) scoring metrics for assessment evaluation * Document how metrics used in the assessment are calculated and state all assumptions * Use the same calculation assumptions and formulas across scopes if possible * List relevant documentation of process and policy as evidentiary support for each score 10*Ceil(x/4) | H3: 0: No items completed | I3: =F3*VALUE(LEFT(H3, FIND(":", H3)-1)) -> 0 | J3: Manage the FinOps Practice | K3: FinOps Assessment
C4: Establish Baselines & Identify Trends | D4: 115 | E4: 1.1.0 | F4: 1 | G4: * Complete an initial assessment for different scopes of the business to establish a baseline * Plot scores over time to track maturity progress for priority scopes * Complete analysis on what contributed to or hindered progress across scopes or different areas of the assessment 10*Ceil(x/3) | H4: 0: No items completed | I4: =F4*VALUE(LEFT(H4, FIND(":", H4)-1)) -> 0 | J4: Manage the FinOps Practice | K4: FinOps Assessment
C5: Prioritize Actions & Publish Roadmap | D5: 116 | E5: 1.1.0 | F5: 1 | G5: 1. Invite subject matter experts (SMEs) and leadership to determine which gaps to address first 2. Determine owners for addressing each of the prioritized gaps 3. Owners will work with relevant teams to scope out how to meet the target score for each gap 4. Work is then scheduled in a roadmap with deadlines that can be tracked at the leadership level | H5: 0: No items completed | I5: =F5*VALUE(LEFT(H5, FIND(":", H5)-1)) -> 0 | J5: Manage the FinOps Practice | K5: FinOps Assessment
C6: Reassess Progress & Update Priorities | D6: 117 | E6: 1.0.0 | F6: 1 | G6: * Schedule a cadence to report progress outcomes to key stakeholders. * Create reporting to show progress on key outcomes across all maturity initiatives. * After successful outcomes are achieved, move on to the next prioritized item in the roadmap. * Periodically reevaluate the gap analysis and priority list based on lessons learned and new business goals. | H6: 0: No items completed | I6: =F6*VALUE(LEFT(H6, FIND(":", H6)-1)) -> 0 | J6: Manage the FinOps Practice | K6: FinOps Assessment
B7: FinOps Education & Enablement | C7: Assess Skills & Training Needs | D7: 097 | E7: 1.0.0 | F7: 1 | H7: 0: Not done | I7: =F7*VALUE(LEFT(H7, FIND(":", H7)-1)) -> 0 | J7: Manage the FinOps Practice | K7: FinOps Education & Enablement
C8: Develop Role-Based Learning Content | D8: 098 | E8: 1.0.0 | F8: 1 | H8: 0: Not done | I8: =F8*VALUE(LEFT(H8, FIND(":", H8)-1)) -> 0 | J8: Manage the FinOps Practice | K8: FinOps Education & Enablement
C9: Offer Certifications & Informal Learning | D9: 099 | E9: 1.0.0 | F9: 1 | H9: 0: Not done | I9: =F9*VALUE(LEFT(H9, FIND(":", H9)-1)) -> 0 | J9: Manage the FinOps Practice | K9: FinOps Education & Enablement
C10: Leverage Vendor Training Resources | D10: 100 | E10: 1.8.0 | F10: 1 | G10: * Define process for reviewing asking for credits from CSPs * Define frequency of review, etc. 10*Ceil(x/2) | H10: 0: No items completed | I10: =F10*VALUE(LEFT(H10, FIND(":", H10)-1)) -> 0 | J10: Manage the FinOps Practice | K10: FinOps Education & Enablement
C11: Track Training Impact & Refresh Content | D11: 101 | E11: 1.0.0 | F11: 1 | H11: 0: Not done | I11: =F11*VALUE(LEFT(H11, FIND(":", H11)-1)) -> 0 | J11: Manage the FinOps Practice | K11: FinOps Education & Enablement
B12: FinOps Practice Operations | C12: Define Org Model & Budget | D12: 091 | E12: 1.8.0 | F12: 1 | H12: 0: Not done | I12: =F12*VALUE(LEFT(H12, FIND(":", H12)-1)) -> 0 | J12: Manage the FinOps Practice | K12: FinOps Practice Operations
C13: Create Implementation Roadmap | D13: 092 | E13: 1.0.0 | F13: 1 | H13: 0: Not done | I13: =F13*VALUE(LEFT(H13, FIND(":", H13)-1)) -> 0 | J13: Manage the FinOps Practice | K13: FinOps Practice Operations
C14: Integrate Cost Data in Workflows | D14: 093 | E14: 1.0.0 | F14: 1 | H14: 0: Not done | I14: =F14*VALUE(LEFT(H14, FIND(":", H14)-1)) -> 0 | J14: Manage the FinOps Practice | K14: FinOps Practice Operations
C15: Publish FinOps KPIs | D15: 094 | E15: 1.0.0 | F15: 1 | H15: 0: Not done | I15: =F15*VALUE(LEFT(H15, FIND(":", H15)-1)) -> 0 | J15: Manage the FinOps Practice | K15: FinOps Practice Operations
C16: Drive Stakeholder Engagement | D16: 095 | E16: 1.0.0 | F16: 1 | H16: 0: Not done | I16: =F16*VALUE(LEFT(H16, FIND(":", H16)-1)) -> 0 | J16: Manage the FinOps Practice | K16: FinOps Practice Operations
C17: Automate Tasks & Review Maturity | D17: 096 | E17: 1.0.0 | F17: 1 | H17: 0: Not done | I17: =F17*VALUE(LEFT(H17, FIND(":", H17)-1)) -> 0 | J17: Manage the FinOps Practice | K17: FinOps Practice Operations
B18: Automation, Tools & Services | C18: Assess Tooling Needs & Criteria | D18: 124 | E18: 1.0.0 | F18: 1 | G18: * Weighted sum Criteria document (score x3), KPI alignment (score x3), Stakeholder count capped at 5 (score x2), Refresh cadence (score x2). Max Raw Score (31) * Criteria formally documented (0=None, 1=Draft, 2=Approved, 3=Versioned+Reviewed) * Criteria explicitly mapped to FinOps KPIs (0=None, 1=Partial, 2=Full) * of FinOps personas involved in criteria definition (0-5) * Criteria review frequency (0=Never, 1=Ad-hoc, 2=Annual, 3=Quarterly+) * Output Range (0 - Max Raw) | H18: 0: Low Maturity (0-9) | I18: =F18*VALUE(LEFT(H18, FIND(":", H18)-1)) -> 0 | J18: Manage the FinOps Practice | K18: Automation, Tools & Services
C19: Evaluate Build vs Buy Options | D19: 125 | E19: 2.1.0 | F19: 1 | G19: * Weighted sum TCO (score x3), Vendor scoring (score x3), Decision document (score x3), Rules established (score x1). Max Raw Score (29) * TCO_Analysis - Total Cost of Ownership analysis performed (0=None, 1=High-level, 2=Detailed, 3=Validated with Finance) * Vendor_Scored - Vendor options scored against criteria (0=None, 1=Informal, 2=Structured scorecard, 3=Multi-stakeholder RFP) * Decision_Doc - Build vs Buy decision formally documented and approved (0=No, 1=Informal note, 2=Formal doc, 3=Exec-approved+reviewed) * Rules_Est - Guiding rules / policy established for future decsions (0=No rules, 1=Draft, 2=Published+Enforced) * Output Range (0 - Max Raw) | H19: 0: Low Maturity. Score Range (0-8) | I19: =F19*VALUE(LEFT(H19, FIND(":", H19)-1)) -> 0 | J19: Manage the FinOps Practice | K19: Automation, Tools & Services
C20: Implement & Configure Tools | D20: 126 | E20: 1.1.0 | F20: 1 | G20: * Weighted sum Env coverage (score x4), Data Integration (score x4), Tag Config (score x2), Config Doc (score x2). Max raw (52) * Env_Coverage - % of cloud environments covered by deployed tools (0=0%, 1<50%, 2=50-79%, 3=80-94%, 4=95-99%, 5=100%) * Data_Integration - Data sources integrated (billing, usage, tags, business context) (0=None, 1=Billing Only, 2=+Usage, 3=+Tags, 4=+Business context, 5=All+Automated) * Tag_Config - Tag/allocation rules configured and enforced tool (0=No, 1=Partial manual, 2=Full manual, 3=Automated enforcement) * Config_Doc - Tool configuration documented and version-controlled (0=No rules, 1=Informal, 2=Documented, 3=Version-controlled+Reviewed) * Output Range (0-52) | H20: 0: Low Maturity. Score Range (0-15) | I20: =F20*VALUE(LEFT(H20, FIND(":", H20)-1)) -> 0 | J20: Manage the FinOps Practice | K20: Automation, Tools & Services
C21: Train Users & Integrate Data | D21: 127 | E21: 1.8.0 | F21: 1 | G21: * Define communication pathways between FinOps and the business * Conduct trainings or create videos * Send out period newsletters * CI/CD governance * Proactive recommendations at deployment 10*Ceil(x/5) | H21: 0: No items completed | I21: =F21*VALUE(LEFT(H21, FIND(":", H21)-1)) -> 0 | J21: Manage the FinOps Practice | K21: Automation, Tools & Services
C22: Monitor Adoption & Iterate Tools | D22: 128 | E22: 1.0.0 | F22: 1 | H22: 0: Not done | I22: =F22*VALUE(LEFT(H22, FIND(":", H22)-1)) -> 0 | J22: Manage the FinOps Practice | K22: Automation, Tools & Services
B23: Intersecting Disciplines | C23: Establish Cross-Team Collab | D23: 129 | E23: 1.1.0 | F23: 1 | G23: 1. Identify key stakeholder teams and key contacts for each (ITAM, SRE, etc.) 2. Document initial thoughts on how this other team may help FinOps goals 3. Document initial thoughts on how the FinOps team may help the other team's goals 4. Reach out to the other team with the initial summary of goals 5. Meet with the other team to better understand how they work | H23: 0: No items completed | I23: =F23*VALUE(LEFT(H23, FIND(":", H23)-1)) -> 0 | J23: Manage the FinOps Practice | K23: Intersecting Disciplines
C24: Align Goals & Data Models | D24: 130 | E24: 1.1.0 | F24: 1 | G24: * Align on new shared goals that will enhance both teams achievements * Determine what data is shared across teams to establish a single source of truth * Identify and agree on tasks that will lead to accomplishing shared goals * Determine which teams have capacity to work on goal tasks periodically * Incorporate tasks into team capacity planning and dependency workflows 10*Ceil(x/5) | H24: 0: No items completed | I24: =F24*VALUE(LEFT(H24, FIND(":", H24)-1)) -> 0 | J24: Manage the FinOps Practice | K24: Intersecting Disciplines
C25: Share Reporting & Definitions | D25: 131 | E25: 1.1.0 | F25: 1 | G25: * Agree on definitions of shared concepts across teams to reduce confusion * Adjust reporting so shared metrics are consistent and from the same source, even if multiple dashboards exist * Regularly align on interpretation of shared metrics to plan next steps and report those to leadership 10*Ceil(x/3) | H25: 0: No items completed | I25: =F25*VALUE(LEFT(H25, FIND(":", H25)-1)) -> 0 | J25: Manage the FinOps Practice | K25: Intersecting Disciplines
C26: Provide Technology Metrics to Teams | D26: 132 | E26: 1.1.0 | F26: 1 | G26: * Share relevant data already maintained and tracked by FinOps * Share metric reporting and the calculations behind FinOps created metrics * Create new metrics from FinOps and other data based on needs of allied teams 10*Ceil(x/3) | H26: 0: No items completed | I26: =F26*VALUE(LEFT(H26, FIND(":", H26)-1)) -> 0 | J26: Manage the FinOps Practice | K26: Intersecting Disciplines
C27: Coordinate Policy Changes Broadly | D27: 133 | E27: 1.1.0 | F27: 1 | G27: 1. Document new policies as a result of cross-functional collaboration goals 2. Broad policy changes are accepted by governing and stakeholder teams 3. Communication is distributed by all governing teams using shared language 4. Change management procedures are followed for updated policy implementation 10*Ceil(x/4) | H27: 0: No items completed | I27: =F27*VALUE(LEFT(H27, FIND(":", H27)-1)) -> 0 | J27: Manage the FinOps Practice | K27: Intersecting Disciplines
C28: Drive Adoption & Resolve Conflicts | D28: 134 | E28: 1.1.0 | F28: 1 | G28: * Come up with shared responses as allied teams to external conflicts * Resolve internal conflicts before deciding on the next steps needed to reach shared goals * Communication to external teams or leaders includes the full story of how allied teams achieve goals together 10*Ceil(x/3) | H28: 0: No items completed | I28: =F28*VALUE(LEFT(H28, FIND(":", H28)-1)) -> 0 | J28: Manage the FinOps Practice | K28: Intersecting Disciplines
B29: Invoicing & Chargeback | C29: Map Invoices to Allocation Model | D29: 107 | E29: 1.0.0 | F29: 1 | H29: 0: Not done | I29: =F29*VALUE(LEFT(H29, FIND(":", H29)-1)) -> 0 | J29: Manage the FinOps Practice | K29: Invoicing & Chargeback
C30: Reconcile Rates & Track Completion | D30: 108 | E30: 1.0.0 | F30: 1 | H30: 0: Not done | I30: =F30*VALUE(LEFT(H30, FIND(":", H30)-1)) -> 0 | J30: Manage the FinOps Practice | K30: Invoicing & Chargeback
C31: Design Chargeback with Finance | D31: 109 | E31: 1.8.0 | F31: 1 | H31: 0: Not done | I31: =F31*VALUE(LEFT(H31, FIND(":", H31)-1)) -> 0 | J31: Manage the FinOps Practice | K31: Invoicing & Chargeback
C32: Automate Chargeback Data Flows | D32: 110 | E32: 1.0.0 | F32: 1 | H32: 0: Not done | I32: =F32*VALUE(LEFT(H32, FIND(":", H32)-1)) -> 0 | J32: Manage the FinOps Practice | K32: Invoicing & Chargeback
C33: Distribute Reports & Track Accuracy | D33: 111 | E33: 1.0.0 | F33: 1 | H33: 0: Not done | I33: =F33*VALUE(LEFT(H33, FIND(":", H33)-1)) -> 0 | J33: Manage the FinOps Practice | K33: Invoicing & Chargeback
C34: Resolve Variances & Increase Coverage | D34: 112 | E34: 1.8.0 | F34: 1 | H34: 0: Not done | I34: =F34*VALUE(LEFT(H34, FIND(":", H34)-1)) -> 0 | J34: Manage the FinOps Practice | K34: Invoicing & Chargeback
B35: Executive Strategy Alignment | C35: Establish Executive Sponsorship | D35: 136 | E35: 1.1.0 | F35: 1 | H35: 0: No executive sponsor identified | I35: =F35*VALUE(LEFT(H35, FIND(":", H35)-1)) -> 0 | J35: Manage the FinOps Practice | K35: Executive Strategy Alignment
C36: Define Decision Rights & Guardrails | D36: 137 | E36: 1.0.0 | F36: 1 | G36: * Document decision rights and approval authority for technology spend * Define and publish spend guardrails with named owners * Establish escalation path for spend exceptions 10*Ceil(x/3) | H36: 0: No items completed | I36: =F36*VALUE(LEFT(H36, FIND(":", H36)-1)) -> 0 | J36: Manage the FinOps Practice | K36: Executive Strategy Alignment
C37: Build Multi-Year Investment Forecast | D37: 138 | E37: 1.0.0 | F37: 1 | G37: * Inventory vendor commitments across technology categories (cloud, SaaS, data center, AI) * Create a multi-year forecast incorporating renewal timelines and growth projections * Incorporate transition and modernization costs into the investment plan 10*Ceil(x/3) | H37: 0: No items completed | I37: =F37*VALUE(LEFT(H37, FIND(":", H37)-1)) -> 0 | J37: Manage the FinOps Practice | K37: Executive Strategy Alignment
C38: Establish Decision Support Cadence | D38: 139 | E38: 1.0.0 | F38: 1 | G38: * Define a regular review cadence for technology investment decisions * Deliver cost and outcome comparisons for competing initiatives at reviews * Track and report action follow-through from investment decisions 10*Ceil(x/3) | H38: 0: No items completed | I38: =F38*VALUE(LEFT(H38, FIND(":", H38)-1)) -> 0 | J38: Manage the FinOps Practice | K38: Executive Strategy Alignment
A39: Usage & Cost | B39: Architecting & Workload Placement | C39: Establish Architecture Review Process | D39: 061 | E39: 1.8.0 | F39: 1 | H39: 0: Does not exist | I39: =F39*VALUE(LEFT(H39, FIND(":", H39)-1)) -> 0 | J39: Usage & Cost | K39: Architecting & Workload Placement
C40: Assess Workloads for Modernization | D40: 062 | E40: 1.8.0 | F40: 1 | G40: * Define process to address notifications from CSPs * Define cadence for review * Define exception criteria * Define thresholds to change * Combine with architecture analysis for SP & RIs 10*Ceil(x/5) | H40: 0: No items completed | I40: =F40*VALUE(LEFT(H40, FIND(":", H40)-1)) -> 0 | J40: Usage & Cost | K40: Architecting & Workload Placement
C41: Estimate Trade-Offs & Document Cases | D41: 063 | E41: 1.8.0 | F41: 1 | H41: 0: No documented method | I41: =F41*VALUE(LEFT(H41, FIND(":", H41)-1)) -> 0 | J41: Usage & Cost | K41: Architecting & Workload Placement
C42: Implement Iteratively & Measure Results | D42: 064 | E42: 2.0.0 | F42: 1 | G42: * Implement architecture changes in time boxed iterations rather than big migrations * Track actual cost outcomes vs estimated savings documented in prior trade off analysis * Define and monitor success metrics (cost delta, performance, reliability) for each iteration * Hold structured retrospectives after each iteration to capture lessons learned * Feed iteration outcomes back into the modernization backlog to reprioritize remaining work 10*Ceil(x/5) | H42: 0: No items completed | I42: =F42*VALUE(LEFT(H42, FIND(":", H42)-1)) -> 0 | J42: Usage & Cost | K42: Architecting & Workload Placement
C43: Publish Benefits & Update References | D43: 065 | E43: 2.0.0 | F43: 1 | G43: * Document and publish cost savings and performance outcomes achieved through architecture changes * Update internal architecture reference guides and design patterns with validated approaches * Share case studies and reusable blueprints with engineering teams to accelerate adoption * Establish a regular cadence to refresh published benefits data and retire outdated references 10*Ceil(x/4) | H43: 0: No items completed | I43: =F43*VALUE(LEFT(H43, FIND(":", H43)-1)) -> 0 | J43: Usage & Cost | K43: Architecting & Workload Placement
C44: Strengthen Architecture Collaboration | D44: 066 | E44: 1.0.0 | F44: 1 | H44: 0: Not done | I44: =F44*VALUE(LEFT(H44, FIND(":", H44)-1)) -> 0 | J44: Usage & Cost | K44: Architecting & Workload Placement
C45: Create Workload Selection Criteria | D45: 118 | E45: 1.0.0 | F45: 1 | H45: 0: Not done | I45: =F45*VALUE(LEFT(H45, FIND(":", H45)-1)) -> 0 | J45: Usage & Cost | K45: Architecting & Workload Placement
C46: Define Success Criteria & Scope | D46: 119 | E46: 1.0.0 | F46: 1 | H46: 0: Not done | I46: =F46*VALUE(LEFT(H46, FIND(":", H46)-1)) -> 0 | J46: Usage & Cost | K46: Architecting & Workload Placement
C47: Enforce Tagging at Onboarding | D47: 120 | E47: 1.8.0 | F47: 1 | G47: * Process defined for new accounts and resources deployed * Train teams on process * Automate process 10*Ceil(x/3) | H47: 0: No items completed | I47: =F47*VALUE(LEFT(H47, FIND(":", H47)-1)) -> 0 | J47: Usage & Cost | K47: Architecting & Workload Placement
C48: Align Timelines with Budgets | D48: 121 | E48: 1.0.0 | F48: 1 | H48: 0: Not done | I48: =F48*VALUE(LEFT(H48, FIND(":", H48)-1)) -> 0 | J48: Usage & Cost | K48: Architecting & Workload Placement
C49: Start with Lower Environments | D49: 122 | E49: 1.0.0 | F49: 1 | H49: 0: Not done | I49: =F49*VALUE(LEFT(H49, FIND(":", H49)-1)) -> 0 | J49: Usage & Cost | K49: Architecting & Workload Placement
C50: Review Outcomes & Adjust Patterns | D50: 123 | E50: 1.0.0 | F50: 1 | H50: 0: Not done | I50: =F50*VALUE(LEFT(H50, FIND(":", H50)-1)) -> 0 | J50: Usage & Cost | K50: Architecting & Workload Placement
B51: Licensing & SaaS | C51: Inventory Licenses & Map Resources | D51: 073 | E51: 1.8.0 | F51: 1 | H51: 0: 0% | I51: =F51*VALUE(LEFT(H51, FIND(":", H51)-1)) -> 0 | J51: Usage & Cost | K51: Licensing & SaaS
C52: Document Licensing Models | D52: 074 | E52: 1.0.0 | F52: 1 | H52: 0: Not done | I52: =F52*VALUE(LEFT(H52, FIND(":", H52)-1)) -> 0 | J52: Usage & Cost | K52: Licensing & SaaS
C53: Integrate Billing with Procurement | D53: 075 | E53: 1.0.0 | F53: 1 | H53: 0: Not done | I53: =F53*VALUE(LEFT(H53, FIND(":", H53)-1)) -> 0 | J53: Usage & Cost | K53: Licensing & SaaS
C54: Validate Utilization & Remediate | D54: 076 | E54: 1.8.0 | F54: 1 | H54: 0: Not done | I54: =F54*VALUE(LEFT(H54, FIND(":", H54)-1)) -> 0 | J54: Usage & Cost | K54: Licensing & SaaS
C55: Influence Workload Design Choices | D55: 077 | E55: 1.0.0 | F55: 1 | H55: 0: Not done | I55: =F55*VALUE(LEFT(H55, FIND(":", H55)-1)) -> 0 | J55: Usage & Cost | K55: Licensing & SaaS
C56: Publish License Spend & Utilization | D56: 078 | E56: 1.0.0 | F56: 1 | H56: 0: Not done | I56: =F56*VALUE(LEFT(H56, FIND(":", H56)-1)) -> 0 | J56: Usage & Cost | K56: Licensing & SaaS
B57: Rate Optimization | C57: Document Commitment Strategy | D57: 079 | E57: 1.8.0 | F57: 1 | H57: 0: Not done | I57: =F57*VALUE(LEFT(H57, FIND(":", H57)-1)) -> 0 | J57: Usage & Cost | K57: Rate Optimization
C58: Build Commitment Analysis Process | D58: 080 | E58: 1.8.0 | F58: 1 | H58: 0: Not done | I58: =F58*VALUE(LEFT(H58, FIND(":", H58)-1)) -> 0 | J58: Usage & Cost | K58: Rate Optimization
C59: Purchase Commitments Regularly | D59: 081 | E59: 1.0.0 | F59: 1 | H59: 0: Not done | I59: =F59*VALUE(LEFT(H59, FIND(":", H59)-1)) -> 0 | J59: Usage & Cost | K59: Rate Optimization
C60: Track ROI & Notify Owners | D60: 082 | E60: 1.0.0 | F60: 1 | H60: 0: Not done | I60: =F60*VALUE(LEFT(H60, FIND(":", H60)-1)) -> 0 | J60: Usage & Cost | K60: Rate Optimization
C61: Allocate Upfront Costs Transparently | D61: 083 | E61: 1.0.0 | F61: 1 | H61: 0: Not done | I61: =F61*VALUE(LEFT(H61, FIND(":", H61)-1)) -> 0 | J61: Usage & Cost | K61: Rate Optimization
C62: Leverage Spot & Negotiated Discounts | D62: 084 | E62: 1.8.0 | F62: 1 | G62: * Process for evaluating spot periodically * Tag for date last reviewed * New deployments get reviewed beforehand * Define requirements for spot * Have exception process and expiration date 10*Ceil(x/5) | H62: 0: No items completed | I62: =F62*VALUE(LEFT(H62, FIND(":", H62)-1)) -> 0 | J62: Usage & Cost | K62: Rate Optimization
B63: Usage Optimization | C63: Define Optimization Strategy | D63: 067 | E63: 1.0.0 | F63: 1 | H63: 0: Not done | I63: =F63*VALUE(LEFT(H63, FIND(":", H63)-1)) -> 0 | J63: Usage & Cost | K63: Usage Optimization
C64: Inventory & Classify Workloads | D64: 068 | E64: 1.8.0 | F64: 1 | H64: 0: No teardown/shutdown policy | I64: =F64*VALUE(LEFT(H64, FIND(":", H64)-1)) -> 0 | J64: Usage & Cost | K64: Usage Optimization
C65: Collect Metrics & Identify Candidates | D65: 069 | E65: 1.8.0 | F65: 1 | H65: 0: 0% | I65: =F65*VALUE(LEFT(H65, FIND(":", H65)-1)) -> 0 | J65: Usage & Cost | K65: Usage Optimization
C66: Partner on Scheduling Actions | D66: 070 | E66: 1.0.0 | F66: 1 | H66: 0: Not done | I66: =F66*VALUE(LEFT(H66, FIND(":", H66)-1)) -> 0 | J66: Usage & Cost | K66: Usage Optimization
C67: Gamify Adoption & Celebrate Wins | D67: 071 | E67: 1.0.0 | F67: 1 | H67: 0: Not done | I67: =F67*VALUE(LEFT(H67, FIND(":", H67)-1)) -> 0 | J67: Usage & Cost | K67: Usage Optimization
C68: Track KPIs & Document Playbooks | D68: 072 | E68: 1.0.0 | F68: 1 | H68: 0: Not done | I68: =F68*VALUE(LEFT(H68, FIND(":", H68)-1)) -> 0 | J68: Usage & Cost | K68: Usage Optimization
B69: Allocation | C69: Define Metadata & Hierarchy Strategy | D69: 009 | E69: 1.8.0 | F69: 1 | G69: Increasing Granularity and Visibility * Define metadata to track (org, dept, cost center, team, app, etc.) * Create the hierarchy for each category of metadata (ex teams per dept, cost centers in an org) 10*Ceil(x/2) | H69: 0: No items completed | I69: =F69*VALUE(LEFT(H69, FIND(":", H69)-1)) -> 0 | J69: Usage & Cost | K69: Allocation
C70: Identify Shared Costs & Rules | D70: 010 | E70: 1.8.0 | F70: 1 | G70: Unallocated Shared CSP Effective Cloud Cost/ Total CSP Effective Cloud Cost | H70: 0: 0% | I70: =F70*VALUE(LEFT(H70, FIND(":", H70)-1)) -> 0 | J70: Usage & Cost | K70: Allocation
C71: Publish Allocation Taxonomy | D71: 011 | E71: 1.8.0 | F71: 1 | G71: Increasing Granularity and Visibility * Document as part of tagging strategy and enforcement * Teams have visibility into where their resources fit into the hierarchy 10*Ceil(x/2) | H71: 0: No items completed | I71: =F71*VALUE(LEFT(H71, FIND(":", H71)-1)) -> 0 | J71: Usage & Cost | K71: Allocation
C72: Implement Tagging Standards | D72: 012 | E72: 1.8.0 | F72: 1 | G72: Percentage of total costs that are tagged for Each Required Tag | H72: 0: 0% | I72: =F72*VALUE(LEFT(H72, FIND(":", H72)-1)) -> 0 | J72: Usage & Cost | K72: Allocation
C73: Validate Compliance & Report Gaps | D73: 013 | E73: 1.8.0 | F73: 1 | G73: x = Total Effective Costs Associated with Unallocated CSP Cloud Resources During y = Total CSP Cloud Costs During a Period of Time x / y | H73: 0: 0% | I73: =F73*VALUE(LEFT(H73, FIND(":", H73)-1)) -> 0 | J73: Usage & Cost | K73: Allocation
C74: Automate Tagging & Enforcement | D74: 014 | E74: 1.8.0 | F74: 1 | G74: Effectiveness/Effort by strategy * Manually asking teams to tag resources * Remove untagged resources after time threshold * Block deployments without proper tags * Automatically tag based on CI/CD creator and team 10*Ceil(x/4) | H74: 0: No items completed | I74: =F74*VALUE(LEFT(H74, FIND(":", H74)-1)) -> 0 | J74: Usage & Cost | K74: Allocation
C75: Iterate Strategies & Communicate | D75: 015 | E75: 1.0.0 | F75: 1 | H75: 0: Not done | I75: =F75*VALUE(LEFT(H75, FIND(":", H75)-1)) -> 0 | J75: Usage & Cost | K75: Allocation
B76: Anomaly Management | C76: Configure Cost Spike Detection | D76: 023 | E76: 1.8.0 | F76: 1 | G76: * Manual inspection of spikes * Out-of-the-box tool based anomaly alerts * Custom simple increase alert calculations * Custom alerts per business unit, team, etc. * Alerts per unit costs above thresholds 10*Ceil(x/5) | H76: 0: No items completed | I76: =F76*VALUE(LEFT(H76, FIND(":", H76)-1)) -> 0 | J76: Usage & Cost | K76: Anomaly Management
C77: Define Severity & Response SLAs | D77: 024 | E77: 1.8.0 | F77: 1 | G77: * Defined severity tiers * Thresholds associated with severity tiers are defined * Defined and adhered to response SLAs * Published response runbooks * Runbook percent successful or completed * RCA completed after alerts 10*Ceil(x/6) | H77: 0: No items completed | I77: =F77*VALUE(LEFT(H77, FIND(":", H77)-1)) -> 0 | J77: Usage & Cost | K77: Anomaly Management
C78: Automate Alert Routing | D78: 025 | E78: 1.8.0 | F78: 1 | H78: 0: No alerting to any owners | I78: =F78*VALUE(LEFT(H78, FIND(":", H78)-1)) -> 0 | J78: Usage & Cost | K78: Anomaly Management
C79: Record Anomaly Context & Timeline | D79: 026 | E79: 1.0.0 | F79: 1 | G79: Denominator: all anomalies detected during the review period. A field item is met when the field is populated on 90% or more of those records. * Single system of record * Scope fields populated (billing account, service, region, and a named accountable owner) * Impact fields populated (variance amount in the reporting currency, and the start and end of the period the variance covers) * Timeline fields populated (first occurrence, detection, notification, and resolution timestamps) * Disposition field populated (true, expected change, or false) * Retention and queryability (records retained for at least 13 months and queryable by scope, disposition, and root cause) 10*Ceil(x/6) | H79: 0: No items completed | I79: =F79*VALUE(LEFT(H79, FIND(":", H79)-1)) -> 0 | J79: Usage & Cost | K79: Anomaly Management
C80: Analyze Root Causes & Fix Issues | D80: 027 | E80: 1.0.0 | F80: 1 | G80: Denominator: anomalies recorded with a true positive disposition during the review period. Items 1 through 4 are met when the stated field is populated on 90% or more of those records. 1. Owner and due date (each record carries a named accountable owner and an analysis due date) 2. Root cause recorded (each record carries a root cause entry naming the change that triggered it) 3. Cause classified (each root cause assigned exactly one category from a published, fixed category list) 4. Remediation recorded (each record carries a remediation action, its completion date, and the measured spend delta over the period following the fix) 5. Preventive control registered (every cause category observed 3 or more times in the trailing 12 months has a linked policy, guardrail, budget, or detection rule) 10*Ceil(x/5) | H80: 0: No items completed | I80: =F80*VALUE(LEFT(H80, FIND(":", H80)-1)) -> 0 | J80: Usage & Cost | K80: Anomaly Management
C81: Track Metrics & Avoidance Rates | D81: 028 | E81: 1.8.0 | F81: 1 | G81: * Number of detections per time period * Number of detections over threshold * Time to send notifications to stakeholders * Time to validate anomaly * Resolution Time/SLA adherence * False positive rate * Cost Avoidance due to detection * Percent anomalies addressed 10*Ceil(x/8) | H81: 0: No items completed | I81: =F81*VALUE(LEFT(H81, FIND(":", H81)-1)) -> 0 | J81: Usage & Cost | K81: Anomaly Management
C82: Tune Thresholds to Reduce Noise | D82: 029 | E82: 1.0.0 | F82: 1 | G82: * Weighted sum Alert precision (score x4), Missed anomalies (score x3), Tuning cadence (score x2), Tuning governance (score x1). Max raw (50) * Alert_Precision: Alerts confirmed as true positives divided by all alerts raised in the review period (0=Not measured, 1<50%, 2=50-69%, 3=70-84%, 4=85-94%, 5=95%+) * Missed_Anomalies: Share of anomalies first found by invoice review, budget variance, or an owner (0=Not measured, 1>25%, 2=10-25%, 3=5-9%, 4=1-4%, 5<1%) * Tuning_Cadence: How often thresholds are reviewed and adjusted against observed outcomes (0=Never, 1=Ad-hoc, 2=Annual, 3=Quarterly, 4=Monthly, 5=Continuous or automated) * Tuning_Governance: How a threshold change is decided and recorded (0=Undocumented, 1=Changed by one person, 2=Documented with rationale, 3=Reviewed with the alert recipients, 4=Version controlled and auditable, 5=Version controlled and replayed against historical anomalies before release) * Output Range (0-50) | H82: 0: Low Maturity. Score Range (0-14) | I82: =F82*VALUE(LEFT(H82, FIND(":", H82)-1)) -> 0 | J82: Usage & Cost | K82: Anomaly Management
B83: Data Ingestion | C83: Inventory All Data Sources | D83: 001 | E83: 1.0.0 | F83: 1 | H83: 0: Not done | I83: =F83*VALUE(LEFT(H83, FIND(":", H83)-1)) -> 0 | J83: Usage & Cost | K83: Data Ingestion
C84: Choose Data Landing Tooling | D84: 002 | E84: 1.0.0 | F84: 1 | H84: 0: Not done | I84: =F84*VALUE(LEFT(H84, FIND(":", H84)-1)) -> 0 | J84: Usage & Cost | K84: Data Ingestion
C85: Create Landing Zones & Controls | D85: 003 | E85: 1.0.0 | F85: 1 | H85: 0: Not done | I85: =F85*VALUE(LEFT(H85, FIND(":", H85)-1)) -> 0 | J85: Usage & Cost | K85: Data Ingestion
C86: Define Data Granularity & Frequency | D86: 004 | E86: 1.8.0 | F86: 1 | H86: 0: Never | I86: =F86*VALUE(LEFT(H86, FIND(":", H86)-1)) -> 0 | J86: Usage & Cost | K86: Data Ingestion
C87: Document Normalization Rules | D87: 005 | E87: 1.0.0 | F87: 1 | H87: 0: Not done | I87: =F87*VALUE(LEFT(H87, FIND(":", H87)-1)) -> 0 | J87: Usage & Cost | K87: Data Ingestion
C88: Implement Data Quality Checks | D88: 006 | E88: 1.8.0 | F88: 1 | G88: * Define data quality (complete, valid, etc.) * Manual quality checks * Automated checks (null % on required fields/tags) * Response process and triage defined * SLAs defined and monitored * Integrate with communication and alerting tools * Integrate into CI/CD pipelines 10*Ceil(x/7) | H88: 0: No items completed | I88: =F88*VALUE(LEFT(H88, FIND(":", H88)-1)) -> 0 | J88: Usage & Cost | K88: Data Ingestion
C89: Build Ingestion Anomaly Dashboards | D89: 007 | E89: 1.8.0 | F89: 1 | G89: Not in order, gain points for each task * Manual or basic logs * Define key metrics (failures, latency, etc.) * Static Dashboard updated manually * Automated alerts for failures * Integrate with communication and alerting tools * Define Process & SLAs:RCAs completed for each * Tune out false positives 10*Ceil(x/7) | H89: 0: No items completed | I89: =F89*VALUE(LEFT(H89, FIND(":", H89)-1)) -> 0 | J89: Usage & Cost | K89: Data Ingestion
C90: Optimize Pipelines for Timeliness | D90: 008 | E90: 1.0.0 | F90: 1 | H90: 0: Not done | I90: =F90*VALUE(LEFT(H90, FIND(":", H90)-1)) -> 0 | J90: Usage & Cost | K90: Data Ingestion
C91: Define Data Ingestion Requirements | D91: 135 | E91: 1.6.1 | F91: 1 | H91: 0: Never | I91: =F91*VALUE(LEFT(H91, FIND(":", H91)-1)) -> 0 | J91: Usage & Cost | K91: Data Ingestion
B92: Reporting & Analytics | C92: Gather Requirements & Define KPIs | D92: 016 | E92: 1.0.0 | F92: 1 | H92: 0: Not done | I92: =F92*VALUE(LEFT(H92, FIND(":", H92)-1)) -> 0 | J92: Usage & Cost | K92: Reporting & Analytics
C93: Enrich Billing with Business Logic | D93: 017 | E93: 1.8.0 | F93: 1 | G93: * Manual adjustments to invoices and teams * Define Business Rules for sharing discounts, RI/SP, etc. * Automate adjustment calculations monthly in arrears * Automate mappings into reporting platform for realtime adjustments 10*Ceil(x/4) | H93: 0: No items completed | I93: =F93*VALUE(LEFT(H93, FIND(":", H93)-1)) -> 0 | J93: Usage & Cost | K93: Reporting & Analytics
C94: Build Dashboards for All Views | D94: 018 | E94: 1.8.0 | F94: 1 | G94: * Dashboard for showback * Dashboard where teams can dive in to investigate costs * Ad-hoc dashboards available to teams * Dashboards for key metrics tracking (tagging, waste, etc.) 10*Ceil(x/4) | H94: 0: No items completed | I94: =F94*VALUE(LEFT(H94, FIND(":", H94)-1)) -> 0 | J94: Usage & Cost | K94: Reporting & Analytics
C95: Publish Documentation & Support | D95: 019 | E95: 1.0.0 | F95: 1 | H95: 0: Not done | I95: =F95*VALUE(LEFT(H95, FIND(":", H95)-1)) -> 0 | J95: Usage & Cost | K95: Reporting & Analytics
C96: Embed Reports in Workflows | D96: 020 | E96: 1.8.0 | F96: 1 | H96: 0: No alerting in workflow tools | I96: =F96*VALUE(LEFT(H96, FIND(":", H96)-1)) -> 0 | J96: Usage & Cost | K96: Reporting & Analytics
C97: Track Adoption & Manage Changes | D97: 021 | E97: 1.0.0 | F97: 1 | H97: 0: Not done | I97: =F97*VALUE(LEFT(H97, FIND(":", H97)-1)) -> 0 | J97: Usage & Cost | K97: Reporting & Analytics
C98: Iterate Based on Feedback | D98: 022 | E98: 1.0.0 | F98: 1 | H98: 0: Not done | I98: =F98*VALUE(LEFT(H98, FIND(":", H98)-1)) -> 0 | J98: Usage & Cost | K98: Reporting & Analytics
A99: Quantify Business Value | B99: KPIs & Benchmarking | C99: Select KPIs & Measurement Scope | D99: 049 | E99: 1.0.0 | F99: 1 | H99: 0: Not done | I99: =F99*VALUE(LEFT(H99, FIND(":", H99)-1)) -> 0 | J99: Quantify Business Value | K99: KPIs & Benchmarking
C100: Validate Tagging for Comparability | D100: 050 | E100: 1.0.0 | F100: 1 | H100: 0: Not done | I100: =F100*VALUE(LEFT(H100, FIND(":", H100)-1)) -> 0 | J100: Quantify Business Value | K100: KPIs & Benchmarking
...
